azure_key_vault_alert/__init__.py
azure_key_vault_alert/azure_key_vault_alert.py
azure_key_vault_alert/post_payloads.py
azure_key_vault_alert/slack_workflow_report.py
ops_py_azure_key_vault_alert-7.0.1.dist-info/LICENSE
ops_py_azure_key_vault_alert-7.0.1.dist-info/METADATA
ops_py_azure_key_vault_alert-7.0.1.dist-info/WHEEL
ops_py_azure_key_vault_alert-7.0.1.dist-info/top_level.txt
ops_py_azure_key_vault_alert-7.0.1.dist-info/RECORD
