Metadata-Version: 2.1
Name: ops-py-azure-key-vault-alert
Version: 7.0.1
Summary: Post Key Vault Secrets report to webhook
License: MIT License
License-File: LICENSE
Requires-Dist: certifi ==2024.6.2
Requires-Dist: charset-normalizer ==3.3.2
Requires-Dist: idna ==3.7
Requires-Dist: ops-py-azure-key-vault-report ==6.0.0
Requires-Dist: ops-py-message-handler ==1.0.4
Requires-Dist: pip ==24.1
Requires-Dist: requests ==2.32.3
Requires-Dist: setuptools ==70.1.1
Requires-Dist: urllib3 ==2.2.2
Requires-Dist: wheel ==0.43.0
